MANIFEST.in
account_statement_demo.xml
account_statement_report.xml
account_statement_view.xml
point_of_sale_data.xml
point_of_sale_demo.xml
point_of_sale_report.xml
point_of_sale_sequence.xml
point_of_sale_view.xml
point_of_sale_workflow.xml
res_partner_view.xml
res_users_view.xml
setup.py
./__init__.py
./__openerp__.py
./account_bank_statement.py
./point_of_sale.py
./res_partner.py
./res_users.py
./controllers/__init__.py
./controllers/main.py
./report/__init__.py
./report/account_statement.py
./report/all_closed_cashbox_of_the_day.py
./report/pos_details.py
./report/pos_details_summary.py
./report/pos_invoice.py
./report/pos_lines.py
./report/pos_order_report.py
./report/pos_payment_report.py
./report/pos_payment_report_user.py
./report/pos_receipt.py
./report/pos_report.py
./report/pos_sales_user.py
./report/pos_sales_user_today.py
./report/pos_users_product.py
./wizard/__init__.py
./wizard/pos_box.py
./wizard/pos_box_entries.py
./wizard/pos_box_out.py
./wizard/pos_confirm.py
./wizard/pos_details.py
./wizard/pos_discount.py
./wizard/pos_open_statement.py
./wizard/pos_payment.py
./wizard/pos_payment_report.py
./wizard/pos_payment_report_user.py
./wizard/pos_receipt.py
./wizard/pos_return.py
./wizard/pos_sales_user.py
./wizard/pos_sales_user_current_user.py
./wizard/pos_sales_user_today.py
./wizard/pos_session_opening.py
doc/barcode_test_sheet.pdf
doc/barcode_test_sheet.svg
doc/barcode_test_sheet2.svg
doc/barcode_test_sheet4.pdf
doc/barcode_test_sheet4.svg
doc/barcode_test_sheet_new.svg
i18n/ar.po
i18n/bg.po
i18n/bs.po
i18n/ca.po
i18n/cs.po
i18n/da.po
i18n/de.po
i18n/el.po
i18n/es.po
i18n/es_AR.po
i18n/es_BO.po
i18n/es_CR.po
i18n/es_EC.po
i18n/es_MX.po
i18n/es_VE.po
i18n/et.po
i18n/fi.po
i18n/fr.po
i18n/he.po
i18n/hi.po
i18n/hr.po
i18n/hu.po
i18n/id.po
i18n/it.po
i18n/ja.po
i18n/ko.po
i18n/lt.po
i18n/lv.po
i18n/mk.po
i18n/mn.po
i18n/nb.po
i18n/nl.po
i18n/nl_BE.po
i18n/pl.po
i18n/point_of_sale.pot
i18n/pt.po
i18n/pt_BR.po
i18n/ro.po
i18n/ru.po
i18n/sl.po
openerp_point_of_sale.egg-info/PKG-INFO
openerp_point_of_sale.egg-info/SOURCES.txt
openerp_point_of_sale.egg-info/dependency_links.txt
openerp_point_of_sale.egg-info/requires.txt
openerp_point_of_sale.egg-info/top_level.txt
